Metadata-Version: 1.0
Name: cstqlorz
Version: 0.0.1
Summary: 陈少太强辣
Home-page: https://waitforaday.site
Author: IcedOtaku
Author-email: i@waitforaday.site
License: UNKNOWN
Platform: UNKNOWN
